datemath-stubs/METADATA.toml
datemath-stubs/__init__.pyi
datemath-stubs/helpers.pyi
datemath-stubs/py.typed
types_python_datemath-3.0.1.20240913.dist-info/METADATA
types_python_datemath-3.0.1.20240913.dist-info/WHEEL
types_python_datemath-3.0.1.20240913.dist-info/top_level.txt
types_python_datemath-3.0.1.20240913.dist-info/RECORD
